<?xml version="1.0" encoding="utf-8"?>
<resources>
<!-- 正尺寸 -->
<dimen name="dp_0">0.00dp</dimen>
<dimen name="dp_1">1.10dp</dimen>
<dimen name="dp_2">2.19dp</dimen>
<dimen name="dp_3">3.29dp</dimen>
<dimen name="dp_4">4.38dp</dimen>
<dimen name="dp_5">5.48dp</dimen>
<dimen name="dp_6">6.58dp</dimen>
<dimen name="dp_7">7.67dp</dimen>
<dimen name="dp_8">8.77dp</dimen>
<dimen name="dp_9">9.86dp</dimen>
<dimen name="dp_10">10.96dp</dimen>
<dimen name="dp_11">12.06dp</dimen>
<dimen name="dp_12">13.15dp</dimen>
<dimen name="dp_13">14.25dp</dimen>
<dimen name="dp_14">15.34dp</dimen>
<dimen name="dp_15">16.44dp</dimen>
<dimen name="dp_16">17.54dp</dimen>
<dimen name="dp_17">18.63dp</dimen>
<dimen name="dp_18">19.73dp</dimen>
<dimen name="dp_19">20.82dp</dimen>
<dimen name="dp_20">21.92dp</dimen>
<dimen name="dp_21">23.02dp</dimen>
<dimen name="dp_22">24.11dp</dimen>
<dimen name="dp_23">25.21dp</dimen>
<dimen name="dp_24">26.30dp</dimen>
<dimen name="dp_25">27.40dp</dimen>
<dimen name="dp_26">28.50dp</dimen>
<dimen name="dp_27">29.59dp</dimen>
<dimen name="dp_28">30.69dp</dimen>
<dimen name="dp_29">31.78dp</dimen>
<dimen name="dp_30">32.88dp</dimen>
<dimen name="dp_31">33.98dp</dimen>
<dimen name="dp_32">35.07dp</dimen>
<dimen name="dp_33">36.17dp</dimen>
<dimen name="dp_34">37.26dp</dimen>
<dimen name="dp_35">38.36dp</dimen>
<dimen name="dp_36">39.46dp</dimen>
<dimen name="dp_37">40.55dp</dimen>
<dimen name="dp_38">41.65dp</dimen>
<dimen name="dp_39">42.74dp</dimen>
<dimen name="dp_40">43.84dp</dimen>
<dimen name="dp_41">44.94dp</dimen>
<dimen name="dp_42">46.03dp</dimen>
<dimen name="dp_43">47.13dp</dimen>
<dimen name="dp_44">48.22dp</dimen>
<dimen name="dp_45">49.32dp</dimen>
<dimen name="dp_46">50.42dp</dimen>
<dimen name="dp_47">51.51dp</dimen>
<dimen name="dp_48">52.61dp</dimen>
<dimen name="dp_49">53.70dp</dimen>
<dimen name="dp_50">54.80dp</dimen>
<dimen name="dp_51">55.90dp</dimen>
<dimen name="dp_52">56.99dp</dimen>
<dimen name="dp_53">58.09dp</dimen>
<dimen name="dp_54">59.18dp</dimen>
<dimen name="dp_55">60.28dp</dimen>
<dimen name="dp_56">61.38dp</dimen>
<dimen name="dp_57">62.47dp</dimen>
<dimen name="dp_58">63.57dp</dimen>
<dimen name="dp_59">64.66dp</dimen>
<dimen name="dp_60">65.76dp</dimen>
<dimen name="dp_61">66.86dp</dimen>
<dimen name="dp_62">67.95dp</dimen>
<dimen name="dp_63">69.05dp</dimen>
<dimen name="dp_64">70.14dp</dimen>
<dimen name="dp_65">71.24dp</dimen>
<dimen name="dp_66">72.34dp</dimen>
<dimen name="dp_67">73.43dp</dimen>
<dimen name="dp_68">74.53dp</dimen>
<dimen name="dp_69">75.62dp</dimen>
<dimen name="dp_70">76.72dp</dimen>
<dimen name="dp_71">77.82dp</dimen>
<dimen name="dp_72">78.91dp</dimen>
<dimen name="dp_73">80.01dp</dimen>
<dimen name="dp_74">81.10dp</dimen>
<dimen name="dp_75">82.20dp</dimen>
<dimen name="dp_76">83.30dp</dimen>
<dimen name="dp_77">84.39dp</dimen>
<dimen name="dp_78">85.49dp</dimen>
<dimen name="dp_79">86.58dp</dimen>
<dimen name="dp_80">87.68dp</dimen>
<dimen name="dp_81">88.78dp</dimen>
<dimen name="dp_82">89.87dp</dimen>
<dimen name="dp_83">90.97dp</dimen>
<dimen name="dp_84">92.06dp</dimen>
<dimen name="dp_85">93.16dp</dimen>
<dimen name="dp_86">94.26dp</dimen>
<dimen name="dp_87">95.35dp</dimen>
<dimen name="dp_88">96.45dp</dimen>
<dimen name="dp_89">97.54dp</dimen>
<dimen name="dp_90">98.64dp</dimen>
<dimen name="dp_91">99.74dp</dimen>
<dimen name="dp_92">100.83dp</dimen>
<dimen name="dp_93">101.93dp</dimen>
<dimen name="dp_94">103.02dp</dimen>
<dimen name="dp_95">104.12dp</dimen>
<dimen name="dp_96">105.22dp</dimen>
<dimen name="dp_97">106.31dp</dimen>
<dimen name="dp_98">107.41dp</dimen>
<dimen name="dp_99">108.50dp</dimen>
<dimen name="dp_100">109.60dp</dimen>
<dimen name="dp_101">110.70dp</dimen>
<dimen name="dp_102">111.79dp</dimen>
<dimen name="dp_103">112.89dp</dimen>
<dimen name="dp_104">113.98dp</dimen>
<dimen name="dp_105">115.08dp</dimen>
<dimen name="dp_106">116.18dp</dimen>
<dimen name="dp_107">117.27dp</dimen>
<dimen name="dp_108">118.37dp</dimen>
<dimen name="dp_109">119.46dp</dimen>
<dimen name="dp_110">120.56dp</dimen>
<dimen name="dp_111">121.66dp</dimen>
<dimen name="dp_112">122.75dp</dimen>
<dimen name="dp_113">123.85dp</dimen>
<dimen name="dp_114">124.94dp</dimen>
<dimen name="dp_115">126.04dp</dimen>
<dimen name="dp_116">127.14dp</dimen>
<dimen name="dp_117">128.23dp</dimen>
<dimen name="dp_118">129.33dp</dimen>
<dimen name="dp_119">130.42dp</dimen>
<dimen name="dp_120">131.52dp</dimen>
<dimen name="dp_121">132.62dp</dimen>
<dimen name="dp_122">133.71dp</dimen>
<dimen name="dp_123">134.81dp</dimen>
<dimen name="dp_124">135.90dp</dimen>
<dimen name="dp_125">137.00dp</dimen>
<dimen name="dp_126">138.10dp</dimen>
<dimen name="dp_127">139.19dp</dimen>
<dimen name="dp_128">140.29dp</dimen>
<dimen name="dp_129">141.38dp</dimen>
<dimen name="dp_130">142.48dp</dimen>
<dimen name="dp_131">143.58dp</dimen>
<dimen name="dp_132">144.67dp</dimen>
<dimen name="dp_133">145.77dp</dimen>
<dimen name="dp_134">146.86dp</dimen>
<dimen name="dp_135">147.96dp</dimen>
<dimen name="dp_136">149.06dp</dimen>
<dimen name="dp_137">150.15dp</dimen>
<dimen name="dp_138">151.25dp</dimen>
<dimen name="dp_139">152.34dp</dimen>
<dimen name="dp_140">153.44dp</dimen>
<dimen name="dp_141">154.54dp</dimen>
<dimen name="dp_142">155.63dp</dimen>
<dimen name="dp_143">156.73dp</dimen>
<dimen name="dp_144">157.82dp</dimen>
<dimen name="dp_145">158.92dp</dimen>
<dimen name="dp_146">160.02dp</dimen>
<dimen name="dp_147">161.11dp</dimen>
<dimen name="dp_148">162.21dp</dimen>
<dimen name="dp_149">163.30dp</dimen>
<dimen name="dp_150">164.40dp</dimen>
<dimen name="dp_151">165.50dp</dimen>
<dimen name="dp_152">166.59dp</dimen>
<dimen name="dp_153">167.69dp</dimen>
<dimen name="dp_154">168.78dp</dimen>
<dimen name="dp_155">169.88dp</dimen>
<dimen name="dp_156">170.98dp</dimen>
<dimen name="dp_157">172.07dp</dimen>
<dimen name="dp_158">173.17dp</dimen>
<dimen name="dp_159">174.26dp</dimen>
<dimen name="dp_160">175.36dp</dimen>
<dimen name="dp_161">176.46dp</dimen>
<dimen name="dp_162">177.55dp</dimen>
<dimen name="dp_163">178.65dp</dimen>
<dimen name="dp_164">179.74dp</dimen>
<dimen name="dp_165">180.84dp</dimen>
<dimen name="dp_166">181.94dp</dimen>
<dimen name="dp_167">183.03dp</dimen>
<dimen name="dp_168">184.13dp</dimen>
<dimen name="dp_169">185.22dp</dimen>
<dimen name="dp_170">186.32dp</dimen>
<dimen name="dp_171">187.42dp</dimen>
<dimen name="dp_172">188.51dp</dimen>
<dimen name="dp_173">189.61dp</dimen>
<dimen name="dp_174">190.70dp</dimen>
<dimen name="dp_175">191.80dp</dimen>
<dimen name="dp_176">192.90dp</dimen>
<dimen name="dp_177">193.99dp</dimen>
<dimen name="dp_178">195.09dp</dimen>
<dimen name="dp_179">196.18dp</dimen>
<dimen name="dp_180">197.28dp</dimen>
<dimen name="dp_181">198.38dp</dimen>
<dimen name="dp_182">199.47dp</dimen>
<dimen name="dp_183">200.57dp</dimen>
<dimen name="dp_184">201.66dp</dimen>
<dimen name="dp_185">202.76dp</dimen>
<dimen name="dp_186">203.86dp</dimen>
<dimen name="dp_187">204.95dp</dimen>
<dimen name="dp_188">206.05dp</dimen>
<dimen name="dp_189">207.14dp</dimen>
<dimen name="dp_190">208.24dp</dimen>
<dimen name="dp_191">209.34dp</dimen>
<dimen name="dp_192">210.43dp</dimen>
<dimen name="dp_193">211.53dp</dimen>
<dimen name="dp_194">212.62dp</dimen>
<dimen name="dp_195">213.72dp</dimen>
<dimen name="dp_196">214.82dp</dimen>
<dimen name="dp_197">215.91dp</dimen>
<dimen name="dp_198">217.01dp</dimen>
<dimen name="dp_199">218.10dp</dimen>
<dimen name="dp_200">219.20dp</dimen>
<dimen name="dp_201">220.30dp</dimen>
<dimen name="dp_202">221.39dp</dimen>
<dimen name="dp_203">222.49dp</dimen>
<dimen name="dp_204">223.58dp</dimen>
<dimen name="dp_205">224.68dp</dimen>
<dimen name="dp_206">225.78dp</dimen>
<dimen name="dp_207">226.87dp</dimen>
<dimen name="dp_208">227.97dp</dimen>
<dimen name="dp_209">229.06dp</dimen>
<dimen name="dp_210">230.16dp</dimen>
<dimen name="dp_211">231.26dp</dimen>
<dimen name="dp_212">232.35dp</dimen>
<dimen name="dp_213">233.45dp</dimen>
<dimen name="dp_214">234.54dp</dimen>
<dimen name="dp_215">235.64dp</dimen>
<dimen name="dp_216">236.74dp</dimen>
<dimen name="dp_217">237.83dp</dimen>
<dimen name="dp_218">238.93dp</dimen>
<dimen name="dp_219">240.02dp</dimen>
<dimen name="dp_220">241.12dp</dimen>
<dimen name="dp_221">242.22dp</dimen>
<dimen name="dp_222">243.31dp</dimen>
<dimen name="dp_223">244.41dp</dimen>
<dimen name="dp_224">245.50dp</dimen>
<dimen name="dp_225">246.60dp</dimen>
<dimen name="dp_226">247.70dp</dimen>
<dimen name="dp_227">248.79dp</dimen>
<dimen name="dp_228">249.89dp</dimen>
<dimen name="dp_229">250.98dp</dimen>
<dimen name="dp_230">252.08dp</dimen>
<dimen name="dp_231">253.18dp</dimen>
<dimen name="dp_232">254.27dp</dimen>
<dimen name="dp_233">255.37dp</dimen>
<dimen name="dp_234">256.46dp</dimen>
<dimen name="dp_235">257.56dp</dimen>
<dimen name="dp_236">258.66dp</dimen>
<dimen name="dp_237">259.75dp</dimen>
<dimen name="dp_238">260.85dp</dimen>
<dimen name="dp_239">261.94dp</dimen>
<dimen name="dp_240">263.04dp</dimen>
<dimen name="dp_241">264.14dp</dimen>
<dimen name="dp_242">265.23dp</dimen>
<dimen name="dp_243">266.33dp</dimen>
<dimen name="dp_244">267.42dp</dimen>
<dimen name="dp_245">268.52dp</dimen>
<dimen name="dp_246">269.62dp</dimen>
<dimen name="dp_247">270.71dp</dimen>
<dimen name="dp_248">271.81dp</dimen>
<dimen name="dp_249">272.90dp</dimen>
<dimen name="dp_250">274.00dp</dimen>
<dimen name="dp_251">275.10dp</dimen>
<dimen name="dp_252">276.19dp</dimen>
<dimen name="dp_253">277.29dp</dimen>
<dimen name="dp_254">278.38dp</dimen>
<dimen name="dp_255">279.48dp</dimen>
<dimen name="dp_256">280.58dp</dimen>
<dimen name="dp_257">281.67dp</dimen>
<dimen name="dp_258">282.77dp</dimen>
<dimen name="dp_259">283.86dp</dimen>
<dimen name="dp_260">284.96dp</dimen>
<dimen name="dp_261">286.06dp</dimen>
<dimen name="dp_262">287.15dp</dimen>
<dimen name="dp_263">288.25dp</dimen>
<dimen name="dp_264">289.34dp</dimen>
<dimen name="dp_265">290.44dp</dimen>
<dimen name="dp_266">291.54dp</dimen>
<dimen name="dp_267">292.63dp</dimen>
<dimen name="dp_268">293.73dp</dimen>
<dimen name="dp_269">294.82dp</dimen>
<dimen name="dp_270">295.92dp</dimen>
<dimen name="dp_271">297.02dp</dimen>
<dimen name="dp_272">298.11dp</dimen>
<dimen name="dp_273">299.21dp</dimen>
<dimen name="dp_274">300.30dp</dimen>
<dimen name="dp_275">301.40dp</dimen>
<dimen name="dp_276">302.50dp</dimen>
<dimen name="dp_277">303.59dp</dimen>
<dimen name="dp_278">304.69dp</dimen>
<dimen name="dp_279">305.78dp</dimen>
<dimen name="dp_280">306.88dp</dimen>
<dimen name="dp_281">307.98dp</dimen>
<dimen name="dp_282">309.07dp</dimen>
<dimen name="dp_283">310.17dp</dimen>
<dimen name="dp_284">311.26dp</dimen>
<dimen name="dp_285">312.36dp</dimen>
<dimen name="dp_286">313.46dp</dimen>
<dimen name="dp_287">314.55dp</dimen>
<dimen name="dp_288">315.65dp</dimen>
<dimen name="dp_289">316.74dp</dimen>
<dimen name="dp_290">317.84dp</dimen>
<dimen name="dp_291">318.94dp</dimen>
<dimen name="dp_292">320.03dp</dimen>
<dimen name="dp_293">321.13dp</dimen>
<dimen name="dp_294">322.22dp</dimen>
<dimen name="dp_295">323.32dp</dimen>
<dimen name="dp_296">324.42dp</dimen>
<dimen name="dp_297">325.51dp</dimen>
<dimen name="dp_298">326.61dp</dimen>
<dimen name="dp_299">327.70dp</dimen>
<dimen name="dp_300">328.80dp</dimen>
<dimen name="dp_301">329.90dp</dimen>
<dimen name="dp_302">330.99dp</dimen>
<dimen name="dp_303">332.09dp</dimen>
<dimen name="dp_304">333.18dp</dimen>
<dimen name="dp_305">334.28dp</dimen>
<dimen name="dp_306">335.38dp</dimen>
<dimen name="dp_307">336.47dp</dimen>
<dimen name="dp_308">337.57dp</dimen>
<dimen name="dp_309">338.66dp</dimen>
<dimen name="dp_310">339.76dp</dimen>
<dimen name="dp_311">340.86dp</dimen>
<dimen name="dp_312">341.95dp</dimen>
<dimen name="dp_313">343.05dp</dimen>
<dimen name="dp_314">344.14dp</dimen>
<dimen name="dp_315">345.24dp</dimen>
<dimen name="dp_316">346.34dp</dimen>
<dimen name="dp_317">347.43dp</dimen>
<dimen name="dp_318">348.53dp</dimen>
<dimen name="dp_319">349.62dp</dimen>
<dimen name="dp_320">350.72dp</dimen>
<dimen name="dp_321">351.82dp</dimen>
<dimen name="dp_322">352.91dp</dimen>
<dimen name="dp_323">354.01dp</dimen>
<dimen name="dp_324">355.10dp</dimen>
<dimen name="dp_325">356.20dp</dimen>
<dimen name="dp_326">357.30dp</dimen>
<dimen name="dp_327">358.39dp</dimen>
<dimen name="dp_328">359.49dp</dimen>
<dimen name="dp_329">360.58dp</dimen>
<dimen name="dp_330">361.68dp</dimen>
<dimen name="dp_331">362.78dp</dimen>
<dimen name="dp_332">363.87dp</dimen>
<dimen name="dp_333">364.97dp</dimen>
<dimen name="dp_334">366.06dp</dimen>
<dimen name="dp_335">367.16dp</dimen>
<dimen name="dp_336">368.26dp</dimen>
<dimen name="dp_337">369.35dp</dimen>
<dimen name="dp_338">370.45dp</dimen>
<dimen name="dp_339">371.54dp</dimen>
<dimen name="dp_340">372.64dp</dimen>
<dimen name="dp_341">373.74dp</dimen>
<dimen name="dp_342">374.83dp</dimen>
<dimen name="dp_343">375.93dp</dimen>
<dimen name="dp_344">377.02dp</dimen>
<dimen name="dp_345">378.12dp</dimen>
<dimen name="dp_346">379.22dp</dimen>
<dimen name="dp_347">380.31dp</dimen>
<dimen name="dp_348">381.41dp</dimen>
<dimen name="dp_349">382.50dp</dimen>
<dimen name="dp_350">383.60dp</dimen>
<dimen name="dp_351">384.70dp</dimen>
<dimen name="dp_352">385.79dp</dimen>
<dimen name="dp_353">386.89dp</dimen>
<dimen name="dp_354">387.98dp</dimen>
<dimen name="dp_355">389.08dp</dimen>
<dimen name="dp_356">390.18dp</dimen>
<dimen name="dp_357">391.27dp</dimen>
<dimen name="dp_358">392.37dp</dimen>
<dimen name="dp_359">393.46dp</dimen>
<dimen name="dp_360">394.56dp</dimen>
<dimen name="dp_361">395.66dp</dimen>
<dimen name="dp_362">396.75dp</dimen>
<dimen name="dp_363">397.85dp</dimen>
<dimen name="dp_364">398.94dp</dimen>
<dimen name="dp_365">400.04dp</dimen>
<dimen name="dp_366">401.14dp</dimen>
<dimen name="dp_367">402.23dp</dimen>
<dimen name="dp_368">403.33dp</dimen>
<dimen name="dp_369">404.42dp</dimen>
<dimen name="dp_370">405.52dp</dimen>
<dimen name="dp_371">406.62dp</dimen>
<dimen name="dp_372">407.71dp</dimen>
<dimen name="dp_373">408.81dp</dimen>
<dimen name="dp_374">409.90dp</dimen>
<dimen name="dp_375">411.00dp</dimen>
<dimen name="dp_376">412.10dp</dimen>
<dimen name="dp_377">413.19dp</dimen>
<dimen name="dp_378">414.29dp</dimen>
<dimen name="dp_379">415.38dp</dimen>
<dimen name="dp_380">416.48dp</dimen>
<dimen name="dp_381">417.58dp</dimen>
<dimen name="dp_382">418.67dp</dimen>
<dimen name="dp_383">419.77dp</dimen>
<dimen name="dp_384">420.86dp</dimen>
<dimen name="dp_385">421.96dp</dimen>
<dimen name="dp_386">423.06dp</dimen>
<dimen name="dp_387">424.15dp</dimen>
<dimen name="dp_388">425.25dp</dimen>
<dimen name="dp_389">426.34dp</dimen>
<dimen name="dp_390">427.44dp</dimen>
<dimen name="dp_391">428.54dp</dimen>
<dimen name="dp_392">429.63dp</dimen>
<dimen name="dp_393">430.73dp</dimen>
<dimen name="dp_394">431.82dp</dimen>
<dimen name="dp_395">432.92dp</dimen>
<dimen name="dp_396">434.02dp</dimen>
<dimen name="dp_397">435.11dp</dimen>
<dimen name="dp_398">436.21dp</dimen>
<dimen name="dp_399">437.30dp</dimen>
<dimen name="dp_400">438.40dp</dimen>
<dimen name="dp_401">439.50dp</dimen>
<dimen name="dp_402">440.59dp</dimen>
<dimen name="dp_403">441.69dp</dimen>
<dimen name="dp_404">442.78dp</dimen>
<dimen name="dp_405">443.88dp</dimen>
<dimen name="dp_406">444.98dp</dimen>
<dimen name="dp_407">446.07dp</dimen>
<dimen name="dp_408">447.17dp</dimen>
<dimen name="dp_409">448.26dp</dimen>
<dimen name="dp_410">449.36dp</dimen>
<dimen name="dp_411">450.46dp</dimen>
<dimen name="dp_412">451.55dp</dimen>
<dimen name="dp_413">452.65dp</dimen>
<dimen name="dp_414">453.74dp</dimen>
<dimen name="dp_415">454.84dp</dimen>
<dimen name="dp_416">455.94dp</dimen>
<dimen name="dp_417">457.03dp</dimen>
<dimen name="dp_418">458.13dp</dimen>
<dimen name="dp_419">459.22dp</dimen>
<dimen name="dp_420">460.32dp</dimen>
<dimen name="dp_421">461.42dp</dimen>
<dimen name="dp_422">462.51dp</dimen>
<dimen name="dp_423">463.61dp</dimen>
<dimen name="dp_424">464.70dp</dimen>
<dimen name="dp_425">465.80dp</dimen>
<dimen name="dp_426">466.90dp</dimen>
<dimen name="dp_427">467.99dp</dimen>
<dimen name="dp_428">469.09dp</dimen>
<dimen name="dp_429">470.18dp</dimen>
<dimen name="dp_430">471.28dp</dimen>
<dimen name="dp_431">472.38dp</dimen>
<dimen name="dp_432">473.47dp</dimen>
<dimen name="dp_433">474.57dp</dimen>
<dimen name="dp_434">475.66dp</dimen>
<dimen name="dp_435">476.76dp</dimen>
<dimen name="dp_436">477.86dp</dimen>
<dimen name="dp_437">478.95dp</dimen>
<dimen name="dp_438">480.05dp</dimen>
<dimen name="dp_439">481.14dp</dimen>
<dimen name="dp_440">482.24dp</dimen>
<dimen name="dp_441">483.34dp</dimen>
<dimen name="dp_442">484.43dp</dimen>
<dimen name="dp_443">485.53dp</dimen>
<dimen name="dp_444">486.62dp</dimen>
<dimen name="dp_445">487.72dp</dimen>
<dimen name="dp_446">488.82dp</dimen>
<dimen name="dp_447">489.91dp</dimen>
<dimen name="dp_448">491.01dp</dimen>
<dimen name="dp_449">492.10dp</dimen>
<dimen name="dp_450">493.20dp</dimen>
<dimen name="dp_451">494.30dp</dimen>
<dimen name="dp_452">495.39dp</dimen>
<dimen name="dp_453">496.49dp</dimen>
<dimen name="dp_454">497.58dp</dimen>
<dimen name="dp_455">498.68dp</dimen>
<dimen name="dp_456">499.78dp</dimen>
<dimen name="dp_457">500.87dp</dimen>
<dimen name="dp_458">501.97dp</dimen>
<dimen name="dp_459">503.06dp</dimen>
<dimen name="dp_460">504.16dp</dimen>
<dimen name="dp_461">505.26dp</dimen>
<dimen name="dp_462">506.35dp</dimen>
<dimen name="dp_463">507.45dp</dimen>
<dimen name="dp_464">508.54dp</dimen>
<dimen name="dp_465">509.64dp</dimen>
<dimen name="dp_466">510.74dp</dimen>
<dimen name="dp_467">511.83dp</dimen>
<dimen name="dp_468">512.93dp</dimen>
<dimen name="dp_469">514.02dp</dimen>
<dimen name="dp_470">515.12dp</dimen>
<dimen name="dp_471">516.22dp</dimen>
<dimen name="dp_472">517.31dp</dimen>
<dimen name="dp_473">518.41dp</dimen>
<dimen name="dp_474">519.50dp</dimen>
<dimen name="dp_475">520.60dp</dimen>
<dimen name="dp_476">521.70dp</dimen>
<dimen name="dp_477">522.79dp</dimen>
<dimen name="dp_478">523.89dp</dimen>
<dimen name="dp_479">524.98dp</dimen>
<dimen name="dp_480">526.08dp</dimen>
<dimen name="dp_481">527.18dp</dimen>
<dimen name="dp_482">528.27dp</dimen>
<dimen name="dp_483">529.37dp</dimen>
<dimen name="dp_484">530.46dp</dimen>
<dimen name="dp_485">531.56dp</dimen>
<dimen name="dp_486">532.66dp</dimen>
<dimen name="dp_487">533.75dp</dimen>
<dimen name="dp_488">534.85dp</dimen>
<dimen name="dp_489">535.94dp</dimen>
<dimen name="dp_490">537.04dp</dimen>
<dimen name="dp_491">538.14dp</dimen>
<dimen name="dp_492">539.23dp</dimen>
<dimen name="dp_493">540.33dp</dimen>
<dimen name="dp_494">541.42dp</dimen>
<dimen name="dp_495">542.52dp</dimen>
<dimen name="dp_496">543.62dp</dimen>
<dimen name="dp_497">544.71dp</dimen>
<dimen name="dp_498">545.81dp</dimen>
<dimen name="dp_499">546.90dp</dimen>
<dimen name="dp_500">548.00dp</dimen>
<dimen name="dp_501">549.10dp</dimen>
<dimen name="dp_502">550.19dp</dimen>
<dimen name="dp_503">551.29dp</dimen>
<dimen name="dp_504">552.38dp</dimen>
<dimen name="dp_505">553.48dp</dimen>
<dimen name="dp_506">554.58dp</dimen>
<dimen name="dp_507">555.67dp</dimen>
<dimen name="dp_508">556.77dp</dimen>
<dimen name="dp_509">557.86dp</dimen>
<dimen name="dp_510">558.96dp</dimen>
<dimen name="dp_511">560.06dp</dimen>
<dimen name="dp_512">561.15dp</dimen>
<dimen name="dp_513">562.25dp</dimen>
<dimen name="dp_514">563.34dp</dimen>
<dimen name="dp_515">564.44dp</dimen>
<dimen name="dp_516">565.54dp</dimen>
<dimen name="dp_517">566.63dp</dimen>
<dimen name="dp_518">567.73dp</dimen>
<dimen name="dp_519">568.82dp</dimen>
<dimen name="dp_520">569.92dp</dimen>
<dimen name="dp_521">571.02dp</dimen>
<dimen name="dp_522">572.11dp</dimen>
<dimen name="dp_523">573.21dp</dimen>
<dimen name="dp_524">574.30dp</dimen>
<dimen name="dp_525">575.40dp</dimen>
<dimen name="dp_526">576.50dp</dimen>
<dimen name="dp_527">577.59dp</dimen>
<dimen name="dp_528">578.69dp</dimen>
<dimen name="dp_529">579.78dp</dimen>
<dimen name="dp_530">580.88dp</dimen>
<dimen name="dp_531">581.98dp</dimen>
<dimen name="dp_532">583.07dp</dimen>
<dimen name="dp_533">584.17dp</dimen>
<dimen name="dp_534">585.26dp</dimen>
<dimen name="dp_535">586.36dp</dimen>
<dimen name="dp_536">587.46dp</dimen>
<dimen name="dp_537">588.55dp</dimen>
<dimen name="dp_538">589.65dp</dimen>
<dimen name="dp_539">590.74dp</dimen>
<dimen name="dp_540">591.84dp</dimen>
<dimen name="dp_541">592.94dp</dimen>
<dimen name="dp_542">594.03dp</dimen>
<dimen name="dp_543">595.13dp</dimen>
<dimen name="dp_544">596.22dp</dimen>
<dimen name="dp_545">597.32dp</dimen>
<dimen name="dp_546">598.42dp</dimen>
<dimen name="dp_547">599.51dp</dimen>
<dimen name="dp_548">600.61dp</dimen>
<dimen name="dp_549">601.70dp</dimen>
<dimen name="dp_550">602.80dp</dimen>
<dimen name="dp_551">603.90dp</dimen>
<dimen name="dp_552">604.99dp</dimen>
<dimen name="dp_553">606.09dp</dimen>
<dimen name="dp_554">607.18dp</dimen>
<dimen name="dp_555">608.28dp</dimen>
<dimen name="dp_556">609.38dp</dimen>
<dimen name="dp_557">610.47dp</dimen>
<dimen name="dp_558">611.57dp</dimen>
<dimen name="dp_559">612.66dp</dimen>
<dimen name="dp_560">613.76dp</dimen>
<dimen name="dp_561">614.86dp</dimen>
<dimen name="dp_562">615.95dp</dimen>
<dimen name="dp_563">617.05dp</dimen>
<dimen name="dp_564">618.14dp</dimen>
<dimen name="dp_565">619.24dp</dimen>
<dimen name="dp_566">620.34dp</dimen>
<dimen name="dp_567">621.43dp</dimen>
<dimen name="dp_568">622.53dp</dimen>
<dimen name="dp_569">623.62dp</dimen>
<dimen name="dp_570">624.72dp</dimen>
<dimen name="dp_571">625.82dp</dimen>
<dimen name="dp_572">626.91dp</dimen>
<dimen name="dp_573">628.01dp</dimen>
<dimen name="dp_574">629.10dp</dimen>
<dimen name="dp_575">630.20dp</dimen>
<dimen name="dp_576">631.30dp</dimen>
<dimen name="dp_577">632.39dp</dimen>
<dimen name="dp_578">633.49dp</dimen>
<dimen name="dp_579">634.58dp</dimen>
<dimen name="dp_580">635.68dp</dimen>
<dimen name="dp_581">636.78dp</dimen>
<dimen name="dp_582">637.87dp</dimen>
<dimen name="dp_583">638.97dp</dimen>
<dimen name="dp_584">640.06dp</dimen>
<dimen name="dp_585">641.16dp</dimen>
<dimen name="dp_586">642.26dp</dimen>
<dimen name="dp_587">643.35dp</dimen>
<dimen name="dp_588">644.45dp</dimen>
<dimen name="dp_589">645.54dp</dimen>
<dimen name="dp_590">646.64dp</dimen>
<dimen name="dp_591">647.74dp</dimen>
<dimen name="dp_592">648.83dp</dimen>
<dimen name="dp_593">649.93dp</dimen>
<dimen name="dp_594">651.02dp</dimen>
<dimen name="dp_595">652.12dp</dimen>
<dimen name="dp_596">653.22dp</dimen>
<dimen name="dp_597">654.31dp</dimen>
<dimen name="dp_598">655.41dp</dimen>
<dimen name="dp_599">656.50dp</dimen>
<dimen name="dp_600">657.60dp</dimen>
<dimen name="dp_601">658.70dp</dimen>
<dimen name="dp_602">659.79dp</dimen>
<dimen name="dp_603">660.89dp</dimen>
<dimen name="dp_604">661.98dp</dimen>
<dimen name="dp_605">663.08dp</dimen>
<dimen name="dp_606">664.18dp</dimen>
<dimen name="dp_607">665.27dp</dimen>
<dimen name="dp_608">666.37dp</dimen>
<dimen name="dp_609">667.46dp</dimen>
<dimen name="dp_610">668.56dp</dimen>
<dimen name="dp_611">669.66dp</dimen>
<dimen name="dp_612">670.75dp</dimen>
<dimen name="dp_613">671.85dp</dimen>
<dimen name="dp_614">672.94dp</dimen>
<dimen name="dp_615">674.04dp</dimen>
<dimen name="dp_616">675.14dp</dimen>
<dimen name="dp_617">676.23dp</dimen>
<dimen name="dp_618">677.33dp</dimen>
<dimen name="dp_619">678.42dp</dimen>
<dimen name="dp_620">679.52dp</dimen>
<dimen name="dp_621">680.62dp</dimen>
<dimen name="dp_622">681.71dp</dimen>
<dimen name="dp_623">682.81dp</dimen>
<dimen name="dp_624">683.90dp</dimen>
<dimen name="dp_625">685.00dp</dimen>
<dimen name="dp_626">686.10dp</dimen>
<dimen name="dp_627">687.19dp</dimen>
<dimen name="dp_628">688.29dp</dimen>
<dimen name="dp_629">689.38dp</dimen>
<dimen name="dp_630">690.48dp</dimen>
<dimen name="dp_631">691.58dp</dimen>
<dimen name="dp_632">692.67dp</dimen>
<dimen name="dp_633">693.77dp</dimen>
<dimen name="dp_634">694.86dp</dimen>
<dimen name="dp_635">695.96dp</dimen>
<dimen name="dp_636">697.06dp</dimen>
<dimen name="dp_637">698.15dp</dimen>
<dimen name="dp_638">699.25dp</dimen>
<dimen name="dp_639">700.34dp</dimen>
<dimen name="dp_640">701.44dp</dimen>
<dimen name="dp_641">702.54dp</dimen>
<dimen name="dp_642">703.63dp</dimen>
<dimen name="dp_643">704.73dp</dimen>
<dimen name="dp_644">705.82dp</dimen>
<dimen name="dp_645">706.92dp</dimen>
<dimen name="dp_646">708.02dp</dimen>
<dimen name="dp_647">709.11dp</dimen>
<dimen name="dp_648">710.21dp</dimen>
<dimen name="dp_649">711.30dp</dimen>
<dimen name="dp_650">712.40dp</dimen>
<dimen name="dp_651">713.50dp</dimen>
<dimen name="dp_652">714.59dp</dimen>
<dimen name="dp_653">715.69dp</dimen>
<dimen name="dp_654">716.78dp</dimen>
<dimen name="dp_655">717.88dp</dimen>
<dimen name="dp_656">718.98dp</dimen>
<dimen name="dp_657">720.07dp</dimen>
<dimen name="dp_658">721.17dp</dimen>
<dimen name="dp_659">722.26dp</dimen>
<dimen name="dp_660">723.36dp</dimen>
<dimen name="dp_661">724.46dp</dimen>
<dimen name="dp_662">725.55dp</dimen>
<dimen name="dp_663">726.65dp</dimen>
<dimen name="dp_664">727.74dp</dimen>
<dimen name="dp_665">728.84dp</dimen>
<dimen name="dp_666">729.94dp</dimen>
<dimen name="dp_667">731.03dp</dimen>
<dimen name="dp_668">732.13dp</dimen>
<dimen name="dp_669">733.22dp</dimen>
<dimen name="dp_670">734.32dp</dimen>
<dimen name="dp_671">735.42dp</dimen>
<dimen name="dp_672">736.51dp</dimen>
<dimen name="dp_673">737.61dp</dimen>
<dimen name="dp_674">738.70dp</dimen>
<dimen name="dp_675">739.80dp</dimen>
<dimen name="dp_676">740.90dp</dimen>
<dimen name="dp_677">741.99dp</dimen>
<dimen name="dp_678">743.09dp</dimen>
<dimen name="dp_679">744.18dp</dimen>
<dimen name="dp_680">745.28dp</dimen>
<dimen name="dp_681">746.38dp</dimen>
<dimen name="dp_682">747.47dp</dimen>
<dimen name="dp_683">748.57dp</dimen>
<dimen name="dp_684">749.66dp</dimen>
<dimen name="dp_685">750.76dp</dimen>
<dimen name="dp_686">751.86dp</dimen>
<dimen name="dp_687">752.95dp</dimen>
<dimen name="dp_688">754.05dp</dimen>
<dimen name="dp_689">755.14dp</dimen>
<dimen name="dp_690">756.24dp</dimen>
<dimen name="dp_691">757.34dp</dimen>
<dimen name="dp_692">758.43dp</dimen>
<dimen name="dp_693">759.53dp</dimen>
<dimen name="dp_694">760.62dp</dimen>
<dimen name="dp_695">761.72dp</dimen>
<dimen name="dp_696">762.82dp</dimen>
<dimen name="dp_697">763.91dp</dimen>
<dimen name="dp_698">765.01dp</dimen>
<dimen name="dp_699">766.10dp</dimen>
<dimen name="dp_700">767.20dp</dimen>
<dimen name="dp_701">768.30dp</dimen>
<dimen name="dp_702">769.39dp</dimen>
<dimen name="dp_703">770.49dp</dimen>
<dimen name="dp_704">771.58dp</dimen>
<dimen name="dp_705">772.68dp</dimen>
<dimen name="dp_706">773.78dp</dimen>
<dimen name="dp_707">774.87dp</dimen>
<dimen name="dp_708">775.97dp</dimen>
<dimen name="dp_709">777.06dp</dimen>
<dimen name="dp_710">778.16dp</dimen>
<dimen name="dp_711">779.26dp</dimen>
<dimen name="dp_712">780.35dp</dimen>
<dimen name="dp_713">781.45dp</dimen>
<dimen name="dp_714">782.54dp</dimen>
<dimen name="dp_715">783.64dp</dimen>
<dimen name="dp_716">784.74dp</dimen>
<dimen name="dp_717">785.83dp</dimen>
<dimen name="dp_718">786.93dp</dimen>
<dimen name="dp_719">788.02dp</dimen>
<dimen name="dp_720">789.12dp</dimen>
<dimen name="dp_721">790.22dp</dimen>
<dimen name="dp_722">791.31dp</dimen>
<dimen name="dp_723">792.41dp</dimen>
<dimen name="dp_724">793.50dp</dimen>
<dimen name="dp_725">794.60dp</dimen>
<dimen name="dp_726">795.70dp</dimen>
<dimen name="dp_727">796.79dp</dimen>
<dimen name="dp_728">797.89dp</dimen>
<dimen name="dp_729">798.98dp</dimen>
<dimen name="dp_730">800.08dp</dimen>
<dimen name="dp_731">801.18dp</dimen>
<dimen name="dp_732">802.27dp</dimen>
<dimen name="dp_733">803.37dp</dimen>
<dimen name="dp_734">804.46dp</dimen>
<dimen name="dp_735">805.56dp</dimen>
<dimen name="dp_736">806.66dp</dimen>
<dimen name="dp_737">807.75dp</dimen>
<dimen name="dp_738">808.85dp</dimen>
<dimen name="dp_739">809.94dp</dimen>
<dimen name="dp_740">811.04dp</dimen>
<dimen name="dp_741">812.14dp</dimen>
<dimen name="dp_742">813.23dp</dimen>
<dimen name="dp_743">814.33dp</dimen>
<dimen name="dp_744">815.42dp</dimen>
<dimen name="dp_745">816.52dp</dimen>
<dimen name="dp_746">817.62dp</dimen>
<dimen name="dp_747">818.71dp</dimen>
<dimen name="dp_748">819.81dp</dimen>
<dimen name="dp_749">820.90dp</dimen>
<dimen name="dp_750">822.00dp</dimen>


<!-- 负尺寸 -->
<dimen name="ndp_0">-0.00dp</dimen>
<dimen name="ndp_1">-1.10dp</dimen>
<dimen name="ndp_2">-2.19dp</dimen>
<dimen name="ndp_3">-3.29dp</dimen>
<dimen name="ndp_4">-4.38dp</dimen>
<dimen name="ndp_5">-5.48dp</dimen>
<dimen name="ndp_6">-6.58dp</dimen>
<dimen name="ndp_7">-7.67dp</dimen>
<dimen name="ndp_8">-8.77dp</dimen>
<dimen name="ndp_9">-9.86dp</dimen>
<dimen name="ndp_10">-10.96dp</dimen>
<dimen name="ndp_11">-12.06dp</dimen>
<dimen name="ndp_12">-13.15dp</dimen>
<dimen name="ndp_13">-14.25dp</dimen>
<dimen name="ndp_14">-15.34dp</dimen>
<dimen name="ndp_15">-16.44dp</dimen>
<dimen name="ndp_16">-17.54dp</dimen>
<dimen name="ndp_17">-18.63dp</dimen>
<dimen name="ndp_18">-19.73dp</dimen>
<dimen name="ndp_19">-20.82dp</dimen>
<dimen name="ndp_20">-21.92dp</dimen>
<dimen name="ndp_21">-23.02dp</dimen>
<dimen name="ndp_22">-24.11dp</dimen>
<dimen name="ndp_23">-25.21dp</dimen>
<dimen name="ndp_24">-26.30dp</dimen>
<dimen name="ndp_25">-27.40dp</dimen>
<dimen name="ndp_26">-28.50dp</dimen>
<dimen name="ndp_27">-29.59dp</dimen>
<dimen name="ndp_28">-30.69dp</dimen>
<dimen name="ndp_29">-31.78dp</dimen>
<dimen name="ndp_30">-32.88dp</dimen>
<dimen name="ndp_31">-33.98dp</dimen>
<dimen name="ndp_32">-35.07dp</dimen>
<dimen name="ndp_33">-36.17dp</dimen>
<dimen name="ndp_34">-37.26dp</dimen>
<dimen name="ndp_35">-38.36dp</dimen>
<dimen name="ndp_36">-39.46dp</dimen>
<dimen name="ndp_37">-40.55dp</dimen>
<dimen name="ndp_38">-41.65dp</dimen>
<dimen name="ndp_39">-42.74dp</dimen>
<dimen name="ndp_40">-43.84dp</dimen>
<dimen name="ndp_41">-44.94dp</dimen>
<dimen name="ndp_42">-46.03dp</dimen>
<dimen name="ndp_43">-47.13dp</dimen>
<dimen name="ndp_44">-48.22dp</dimen>
<dimen name="ndp_45">-49.32dp</dimen>
<dimen name="ndp_46">-50.42dp</dimen>
<dimen name="ndp_47">-51.51dp</dimen>
<dimen name="ndp_48">-52.61dp</dimen>
<dimen name="ndp_49">-53.70dp</dimen>
<dimen name="ndp_50">-54.80dp</dimen>
<dimen name="ndp_51">-55.90dp</dimen>
<dimen name="ndp_52">-56.99dp</dimen>
<dimen name="ndp_53">-58.09dp</dimen>
<dimen name="ndp_54">-59.18dp</dimen>
<dimen name="ndp_55">-60.28dp</dimen>
<dimen name="ndp_56">-61.38dp</dimen>
<dimen name="ndp_57">-62.47dp</dimen>
<dimen name="ndp_58">-63.57dp</dimen>
<dimen name="ndp_59">-64.66dp</dimen>
<dimen name="ndp_60">-65.76dp</dimen>
<dimen name="ndp_61">-66.86dp</dimen>
<dimen name="ndp_62">-67.95dp</dimen>
<dimen name="ndp_63">-69.05dp</dimen>
<dimen name="ndp_64">-70.14dp</dimen>
<dimen name="ndp_65">-71.24dp</dimen>
<dimen name="ndp_66">-72.34dp</dimen>
<dimen name="ndp_67">-73.43dp</dimen>
<dimen name="ndp_68">-74.53dp</dimen>
<dimen name="ndp_69">-75.62dp</dimen>
<dimen name="ndp_70">-76.72dp</dimen>
<dimen name="ndp_71">-77.82dp</dimen>
<dimen name="ndp_72">-78.91dp</dimen>
<dimen name="ndp_73">-80.01dp</dimen>
<dimen name="ndp_74">-81.10dp</dimen>
<dimen name="ndp_75">-82.20dp</dimen>
<dimen name="ndp_76">-83.30dp</dimen>
<dimen name="ndp_77">-84.39dp</dimen>
<dimen name="ndp_78">-85.49dp</dimen>
<dimen name="ndp_79">-86.58dp</dimen>
<dimen name="ndp_80">-87.68dp</dimen>
<dimen name="ndp_81">-88.78dp</dimen>
<dimen name="ndp_82">-89.87dp</dimen>
<dimen name="ndp_83">-90.97dp</dimen>
<dimen name="ndp_84">-92.06dp</dimen>
<dimen name="ndp_85">-93.16dp</dimen>
<dimen name="ndp_86">-94.26dp</dimen>
<dimen name="ndp_87">-95.35dp</dimen>
<dimen name="ndp_88">-96.45dp</dimen>
<dimen name="ndp_89">-97.54dp</dimen>
<dimen name="ndp_90">-98.64dp</dimen>
<dimen name="ndp_91">-99.74dp</dimen>
<dimen name="ndp_92">-100.83dp</dimen>
<dimen name="ndp_93">-101.93dp</dimen>
<dimen name="ndp_94">-103.02dp</dimen>
<dimen name="ndp_95">-104.12dp</dimen>
<dimen name="ndp_96">-105.22dp</dimen>
<dimen name="ndp_97">-106.31dp</dimen>
<dimen name="ndp_98">-107.41dp</dimen>
<dimen name="ndp_99">-108.50dp</dimen>
<dimen name="ndp_100">-109.60dp</dimen>
<dimen name="ndp_101">-110.70dp</dimen>
<dimen name="ndp_102">-111.79dp</dimen>
<dimen name="ndp_103">-112.89dp</dimen>
<dimen name="ndp_104">-113.98dp</dimen>
<dimen name="ndp_105">-115.08dp</dimen>
<dimen name="ndp_106">-116.18dp</dimen>
<dimen name="ndp_107">-117.27dp</dimen>
<dimen name="ndp_108">-118.37dp</dimen>
<dimen name="ndp_109">-119.46dp</dimen>
<dimen name="ndp_110">-120.56dp</dimen>
<dimen name="ndp_111">-121.66dp</dimen>
<dimen name="ndp_112">-122.75dp</dimen>
<dimen name="ndp_113">-123.85dp</dimen>
<dimen name="ndp_114">-124.94dp</dimen>
<dimen name="ndp_115">-126.04dp</dimen>
<dimen name="ndp_116">-127.14dp</dimen>
<dimen name="ndp_117">-128.23dp</dimen>
<dimen name="ndp_118">-129.33dp</dimen>
<dimen name="ndp_119">-130.42dp</dimen>
<dimen name="ndp_120">-131.52dp</dimen>
<dimen name="ndp_121">-132.62dp</dimen>
<dimen name="ndp_122">-133.71dp</dimen>
<dimen name="ndp_123">-134.81dp</dimen>
<dimen name="ndp_124">-135.90dp</dimen>
<dimen name="ndp_125">-137.00dp</dimen>
<dimen name="ndp_126">-138.10dp</dimen>
<dimen name="ndp_127">-139.19dp</dimen>
<dimen name="ndp_128">-140.29dp</dimen>
<dimen name="ndp_129">-141.38dp</dimen>
<dimen name="ndp_130">-142.48dp</dimen>
<dimen name="ndp_131">-143.58dp</dimen>
<dimen name="ndp_132">-144.67dp</dimen>
<dimen name="ndp_133">-145.77dp</dimen>
<dimen name="ndp_134">-146.86dp</dimen>
<dimen name="ndp_135">-147.96dp</dimen>
<dimen name="ndp_136">-149.06dp</dimen>
<dimen name="ndp_137">-150.15dp</dimen>
<dimen name="ndp_138">-151.25dp</dimen>
<dimen name="ndp_139">-152.34dp</dimen>
<dimen name="ndp_140">-153.44dp</dimen>
<dimen name="ndp_141">-154.54dp</dimen>
<dimen name="ndp_142">-155.63dp</dimen>
<dimen name="ndp_143">-156.73dp</dimen>
<dimen name="ndp_144">-157.82dp</dimen>
<dimen name="ndp_145">-158.92dp</dimen>
<dimen name="ndp_146">-160.02dp</dimen>
<dimen name="ndp_147">-161.11dp</dimen>
<dimen name="ndp_148">-162.21dp</dimen>
<dimen name="ndp_149">-163.30dp</dimen>
<dimen name="ndp_150">-164.40dp</dimen>
<dimen name="ndp_151">-165.50dp</dimen>
<dimen name="ndp_152">-166.59dp</dimen>
<dimen name="ndp_153">-167.69dp</dimen>
<dimen name="ndp_154">-168.78dp</dimen>
<dimen name="ndp_155">-169.88dp</dimen>
<dimen name="ndp_156">-170.98dp</dimen>
<dimen name="ndp_157">-172.07dp</dimen>
<dimen name="ndp_158">-173.17dp</dimen>
<dimen name="ndp_159">-174.26dp</dimen>
<dimen name="ndp_160">-175.36dp</dimen>
<dimen name="ndp_161">-176.46dp</dimen>
<dimen name="ndp_162">-177.55dp</dimen>
<dimen name="ndp_163">-178.65dp</dimen>
<dimen name="ndp_164">-179.74dp</dimen>
<dimen name="ndp_165">-180.84dp</dimen>
<dimen name="ndp_166">-181.94dp</dimen>
<dimen name="ndp_167">-183.03dp</dimen>
<dimen name="ndp_168">-184.13dp</dimen>
<dimen name="ndp_169">-185.22dp</dimen>
<dimen name="ndp_170">-186.32dp</dimen>
<dimen name="ndp_171">-187.42dp</dimen>
<dimen name="ndp_172">-188.51dp</dimen>
<dimen name="ndp_173">-189.61dp</dimen>
<dimen name="ndp_174">-190.70dp</dimen>
<dimen name="ndp_175">-191.80dp</dimen>
<dimen name="ndp_176">-192.90dp</dimen>
<dimen name="ndp_177">-193.99dp</dimen>
<dimen name="ndp_178">-195.09dp</dimen>
<dimen name="ndp_179">-196.18dp</dimen>
<dimen name="ndp_180">-197.28dp</dimen>
<dimen name="ndp_181">-198.38dp</dimen>
<dimen name="ndp_182">-199.47dp</dimen>
<dimen name="ndp_183">-200.57dp</dimen>
<dimen name="ndp_184">-201.66dp</dimen>
<dimen name="ndp_185">-202.76dp</dimen>
<dimen name="ndp_186">-203.86dp</dimen>
<dimen name="ndp_187">-204.95dp</dimen>
<dimen name="ndp_188">-206.05dp</dimen>
<dimen name="ndp_189">-207.14dp</dimen>
<dimen name="ndp_190">-208.24dp</dimen>
<dimen name="ndp_191">-209.34dp</dimen>
<dimen name="ndp_192">-210.43dp</dimen>
<dimen name="ndp_193">-211.53dp</dimen>
<dimen name="ndp_194">-212.62dp</dimen>
<dimen name="ndp_195">-213.72dp</dimen>
<dimen name="ndp_196">-214.82dp</dimen>
<dimen name="ndp_197">-215.91dp</dimen>
<dimen name="ndp_198">-217.01dp</dimen>
<dimen name="ndp_199">-218.10dp</dimen>
<dimen name="ndp_200">-219.20dp</dimen>
<dimen name="ndp_201">-220.30dp</dimen>
<dimen name="ndp_202">-221.39dp</dimen>
<dimen name="ndp_203">-222.49dp</dimen>
<dimen name="ndp_204">-223.58dp</dimen>
<dimen name="ndp_205">-224.68dp</dimen>
<dimen name="ndp_206">-225.78dp</dimen>
<dimen name="ndp_207">-226.87dp</dimen>
<dimen name="ndp_208">-227.97dp</dimen>
<dimen name="ndp_209">-229.06dp</dimen>
<dimen name="ndp_210">-230.16dp</dimen>
<dimen name="ndp_211">-231.26dp</dimen>
<dimen name="ndp_212">-232.35dp</dimen>
<dimen name="ndp_213">-233.45dp</dimen>
<dimen name="ndp_214">-234.54dp</dimen>
<dimen name="ndp_215">-235.64dp</dimen>
<dimen name="ndp_216">-236.74dp</dimen>
<dimen name="ndp_217">-237.83dp</dimen>
<dimen name="ndp_218">-238.93dp</dimen>
<dimen name="ndp_219">-240.02dp</dimen>
<dimen name="ndp_220">-241.12dp</dimen>
<dimen name="ndp_221">-242.22dp</dimen>
<dimen name="ndp_222">-243.31dp</dimen>
<dimen name="ndp_223">-244.41dp</dimen>
<dimen name="ndp_224">-245.50dp</dimen>
<dimen name="ndp_225">-246.60dp</dimen>
<dimen name="ndp_226">-247.70dp</dimen>
<dimen name="ndp_227">-248.79dp</dimen>
<dimen name="ndp_228">-249.89dp</dimen>
<dimen name="ndp_229">-250.98dp</dimen>
<dimen name="ndp_230">-252.08dp</dimen>
<dimen name="ndp_231">-253.18dp</dimen>
<dimen name="ndp_232">-254.27dp</dimen>
<dimen name="ndp_233">-255.37dp</dimen>
<dimen name="ndp_234">-256.46dp</dimen>
<dimen name="ndp_235">-257.56dp</dimen>
<dimen name="ndp_236">-258.66dp</dimen>
<dimen name="ndp_237">-259.75dp</dimen>
<dimen name="ndp_238">-260.85dp</dimen>
<dimen name="ndp_239">-261.94dp</dimen>
<dimen name="ndp_240">-263.04dp</dimen>
<dimen name="ndp_241">-264.14dp</dimen>
<dimen name="ndp_242">-265.23dp</dimen>
<dimen name="ndp_243">-266.33dp</dimen>
<dimen name="ndp_244">-267.42dp</dimen>
<dimen name="ndp_245">-268.52dp</dimen>
<dimen name="ndp_246">-269.62dp</dimen>
<dimen name="ndp_247">-270.71dp</dimen>
<dimen name="ndp_248">-271.81dp</dimen>
<dimen name="ndp_249">-272.90dp</dimen>
<dimen name="ndp_250">-274.00dp</dimen>
<dimen name="ndp_251">-275.10dp</dimen>
<dimen name="ndp_252">-276.19dp</dimen>
<dimen name="ndp_253">-277.29dp</dimen>
<dimen name="ndp_254">-278.38dp</dimen>
<dimen name="ndp_255">-279.48dp</dimen>
<dimen name="ndp_256">-280.58dp</dimen>
<dimen name="ndp_257">-281.67dp</dimen>
<dimen name="ndp_258">-282.77dp</dimen>
<dimen name="ndp_259">-283.86dp</dimen>
<dimen name="ndp_260">-284.96dp</dimen>
<dimen name="ndp_261">-286.06dp</dimen>
<dimen name="ndp_262">-287.15dp</dimen>
<dimen name="ndp_263">-288.25dp</dimen>
<dimen name="ndp_264">-289.34dp</dimen>
<dimen name="ndp_265">-290.44dp</dimen>
<dimen name="ndp_266">-291.54dp</dimen>
<dimen name="ndp_267">-292.63dp</dimen>
<dimen name="ndp_268">-293.73dp</dimen>
<dimen name="ndp_269">-294.82dp</dimen>
<dimen name="ndp_270">-295.92dp</dimen>
<dimen name="ndp_271">-297.02dp</dimen>
<dimen name="ndp_272">-298.11dp</dimen>
<dimen name="ndp_273">-299.21dp</dimen>
<dimen name="ndp_274">-300.30dp</dimen>
<dimen name="ndp_275">-301.40dp</dimen>
<dimen name="ndp_276">-302.50dp</dimen>
<dimen name="ndp_277">-303.59dp</dimen>
<dimen name="ndp_278">-304.69dp</dimen>
<dimen name="ndp_279">-305.78dp</dimen>
<dimen name="ndp_280">-306.88dp</dimen>
<dimen name="ndp_281">-307.98dp</dimen>
<dimen name="ndp_282">-309.07dp</dimen>
<dimen name="ndp_283">-310.17dp</dimen>
<dimen name="ndp_284">-311.26dp</dimen>
<dimen name="ndp_285">-312.36dp</dimen>
<dimen name="ndp_286">-313.46dp</dimen>
<dimen name="ndp_287">-314.55dp</dimen>
<dimen name="ndp_288">-315.65dp</dimen>
<dimen name="ndp_289">-316.74dp</dimen>
<dimen name="ndp_290">-317.84dp</dimen>
<dimen name="ndp_291">-318.94dp</dimen>
<dimen name="ndp_292">-320.03dp</dimen>
<dimen name="ndp_293">-321.13dp</dimen>
<dimen name="ndp_294">-322.22dp</dimen>
<dimen name="ndp_295">-323.32dp</dimen>
<dimen name="ndp_296">-324.42dp</dimen>
<dimen name="ndp_297">-325.51dp</dimen>
<dimen name="ndp_298">-326.61dp</dimen>
<dimen name="ndp_299">-327.70dp</dimen>
<dimen name="ndp_300">-328.80dp</dimen>
<dimen name="ndp_301">-329.90dp</dimen>
<dimen name="ndp_302">-330.99dp</dimen>
<dimen name="ndp_303">-332.09dp</dimen>
<dimen name="ndp_304">-333.18dp</dimen>
<dimen name="ndp_305">-334.28dp</dimen>
<dimen name="ndp_306">-335.38dp</dimen>
<dimen name="ndp_307">-336.47dp</dimen>
<dimen name="ndp_308">-337.57dp</dimen>
<dimen name="ndp_309">-338.66dp</dimen>
<dimen name="ndp_310">-339.76dp</dimen>
<dimen name="ndp_311">-340.86dp</dimen>
<dimen name="ndp_312">-341.95dp</dimen>
<dimen name="ndp_313">-343.05dp</dimen>
<dimen name="ndp_314">-344.14dp</dimen>
<dimen name="ndp_315">-345.24dp</dimen>
<dimen name="ndp_316">-346.34dp</dimen>
<dimen name="ndp_317">-347.43dp</dimen>
<dimen name="ndp_318">-348.53dp</dimen>
<dimen name="ndp_319">-349.62dp</dimen>
<dimen name="ndp_320">-350.72dp</dimen>
<dimen name="ndp_321">-351.82dp</dimen>
<dimen name="ndp_322">-352.91dp</dimen>
<dimen name="ndp_323">-354.01dp</dimen>
<dimen name="ndp_324">-355.10dp</dimen>
<dimen name="ndp_325">-356.20dp</dimen>
<dimen name="ndp_326">-357.30dp</dimen>
<dimen name="ndp_327">-358.39dp</dimen>
<dimen name="ndp_328">-359.49dp</dimen>
<dimen name="ndp_329">-360.58dp</dimen>
<dimen name="ndp_330">-361.68dp</dimen>
<dimen name="ndp_331">-362.78dp</dimen>
<dimen name="ndp_332">-363.87dp</dimen>
<dimen name="ndp_333">-364.97dp</dimen>
<dimen name="ndp_334">-366.06dp</dimen>
<dimen name="ndp_335">-367.16dp</dimen>
<dimen name="ndp_336">-368.26dp</dimen>
<dimen name="ndp_337">-369.35dp</dimen>
<dimen name="ndp_338">-370.45dp</dimen>
<dimen name="ndp_339">-371.54dp</dimen>
<dimen name="ndp_340">-372.64dp</dimen>
<dimen name="ndp_341">-373.74dp</dimen>
<dimen name="ndp_342">-374.83dp</dimen>
<dimen name="ndp_343">-375.93dp</dimen>
<dimen name="ndp_344">-377.02dp</dimen>
<dimen name="ndp_345">-378.12dp</dimen>
<dimen name="ndp_346">-379.22dp</dimen>
<dimen name="ndp_347">-380.31dp</dimen>
<dimen name="ndp_348">-381.41dp</dimen>
<dimen name="ndp_349">-382.50dp</dimen>
<dimen name="ndp_350">-383.60dp</dimen>
<dimen name="ndp_351">-384.70dp</dimen>
<dimen name="ndp_352">-385.79dp</dimen>
<dimen name="ndp_353">-386.89dp</dimen>
<dimen name="ndp_354">-387.98dp</dimen>
<dimen name="ndp_355">-389.08dp</dimen>
<dimen name="ndp_356">-390.18dp</dimen>
<dimen name="ndp_357">-391.27dp</dimen>
<dimen name="ndp_358">-392.37dp</dimen>
<dimen name="ndp_359">-393.46dp</dimen>
<dimen name="ndp_360">-394.56dp</dimen>
<dimen name="ndp_361">-395.66dp</dimen>
<dimen name="ndp_362">-396.75dp</dimen>
<dimen name="ndp_363">-397.85dp</dimen>
<dimen name="ndp_364">-398.94dp</dimen>
<dimen name="ndp_365">-400.04dp</dimen>
<dimen name="ndp_366">-401.14dp</dimen>
<dimen name="ndp_367">-402.23dp</dimen>
<dimen name="ndp_368">-403.33dp</dimen>
<dimen name="ndp_369">-404.42dp</dimen>
<dimen name="ndp_370">-405.52dp</dimen>
<dimen name="ndp_371">-406.62dp</dimen>
<dimen name="ndp_372">-407.71dp</dimen>
<dimen name="ndp_373">-408.81dp</dimen>
<dimen name="ndp_374">-409.90dp</dimen>
<dimen name="ndp_375">-411.00dp</dimen>
<dimen name="ndp_376">-412.10dp</dimen>
<dimen name="ndp_377">-413.19dp</dimen>
<dimen name="ndp_378">-414.29dp</dimen>
<dimen name="ndp_379">-415.38dp</dimen>
<dimen name="ndp_380">-416.48dp</dimen>
<dimen name="ndp_381">-417.58dp</dimen>
<dimen name="ndp_382">-418.67dp</dimen>
<dimen name="ndp_383">-419.77dp</dimen>
<dimen name="ndp_384">-420.86dp</dimen>
<dimen name="ndp_385">-421.96dp</dimen>
<dimen name="ndp_386">-423.06dp</dimen>
<dimen name="ndp_387">-424.15dp</dimen>
<dimen name="ndp_388">-425.25dp</dimen>
<dimen name="ndp_389">-426.34dp</dimen>
<dimen name="ndp_390">-427.44dp</dimen>
<dimen name="ndp_391">-428.54dp</dimen>
<dimen name="ndp_392">-429.63dp</dimen>
<dimen name="ndp_393">-430.73dp</dimen>
<dimen name="ndp_394">-431.82dp</dimen>
<dimen name="ndp_395">-432.92dp</dimen>
<dimen name="ndp_396">-434.02dp</dimen>
<dimen name="ndp_397">-435.11dp</dimen>
<dimen name="ndp_398">-436.21dp</dimen>
<dimen name="ndp_399">-437.30dp</dimen>
<dimen name="ndp_400">-438.40dp</dimen>
<dimen name="ndp_401">-439.50dp</dimen>
<dimen name="ndp_402">-440.59dp</dimen>
<dimen name="ndp_403">-441.69dp</dimen>
<dimen name="ndp_404">-442.78dp</dimen>
<dimen name="ndp_405">-443.88dp</dimen>
<dimen name="ndp_406">-444.98dp</dimen>
<dimen name="ndp_407">-446.07dp</dimen>
<dimen name="ndp_408">-447.17dp</dimen>
<dimen name="ndp_409">-448.26dp</dimen>
<dimen name="ndp_410">-449.36dp</dimen>
<dimen name="ndp_411">-450.46dp</dimen>
<dimen name="ndp_412">-451.55dp</dimen>
<dimen name="ndp_413">-452.65dp</dimen>
<dimen name="ndp_414">-453.74dp</dimen>
<dimen name="ndp_415">-454.84dp</dimen>
<dimen name="ndp_416">-455.94dp</dimen>
<dimen name="ndp_417">-457.03dp</dimen>
<dimen name="ndp_418">-458.13dp</dimen>
<dimen name="ndp_419">-459.22dp</dimen>
<dimen name="ndp_420">-460.32dp</dimen>
<dimen name="ndp_421">-461.42dp</dimen>
<dimen name="ndp_422">-462.51dp</dimen>
<dimen name="ndp_423">-463.61dp</dimen>
<dimen name="ndp_424">-464.70dp</dimen>
<dimen name="ndp_425">-465.80dp</dimen>
<dimen name="ndp_426">-466.90dp</dimen>
<dimen name="ndp_427">-467.99dp</dimen>
<dimen name="ndp_428">-469.09dp</dimen>
<dimen name="ndp_429">-470.18dp</dimen>
<dimen name="ndp_430">-471.28dp</dimen>
<dimen name="ndp_431">-472.38dp</dimen>
<dimen name="ndp_432">-473.47dp</dimen>
<dimen name="ndp_433">-474.57dp</dimen>
<dimen name="ndp_434">-475.66dp</dimen>
<dimen name="ndp_435">-476.76dp</dimen>
<dimen name="ndp_436">-477.86dp</dimen>
<dimen name="ndp_437">-478.95dp</dimen>
<dimen name="ndp_438">-480.05dp</dimen>
<dimen name="ndp_439">-481.14dp</dimen>
<dimen name="ndp_440">-482.24dp</dimen>
<dimen name="ndp_441">-483.34dp</dimen>
<dimen name="ndp_442">-484.43dp</dimen>
<dimen name="ndp_443">-485.53dp</dimen>
<dimen name="ndp_444">-486.62dp</dimen>
<dimen name="ndp_445">-487.72dp</dimen>
<dimen name="ndp_446">-488.82dp</dimen>
<dimen name="ndp_447">-489.91dp</dimen>
<dimen name="ndp_448">-491.01dp</dimen>
<dimen name="ndp_449">-492.10dp</dimen>
<dimen name="ndp_450">-493.20dp</dimen>
<dimen name="ndp_451">-494.30dp</dimen>
<dimen name="ndp_452">-495.39dp</dimen>
<dimen name="ndp_453">-496.49dp</dimen>
<dimen name="ndp_454">-497.58dp</dimen>
<dimen name="ndp_455">-498.68dp</dimen>
<dimen name="ndp_456">-499.78dp</dimen>
<dimen name="ndp_457">-500.87dp</dimen>
<dimen name="ndp_458">-501.97dp</dimen>
<dimen name="ndp_459">-503.06dp</dimen>
<dimen name="ndp_460">-504.16dp</dimen>
<dimen name="ndp_461">-505.26dp</dimen>
<dimen name="ndp_462">-506.35dp</dimen>
<dimen name="ndp_463">-507.45dp</dimen>
<dimen name="ndp_464">-508.54dp</dimen>
<dimen name="ndp_465">-509.64dp</dimen>
<dimen name="ndp_466">-510.74dp</dimen>
<dimen name="ndp_467">-511.83dp</dimen>
<dimen name="ndp_468">-512.93dp</dimen>
<dimen name="ndp_469">-514.02dp</dimen>
<dimen name="ndp_470">-515.12dp</dimen>
<dimen name="ndp_471">-516.22dp</dimen>
<dimen name="ndp_472">-517.31dp</dimen>
<dimen name="ndp_473">-518.41dp</dimen>
<dimen name="ndp_474">-519.50dp</dimen>
<dimen name="ndp_475">-520.60dp</dimen>
<dimen name="ndp_476">-521.70dp</dimen>
<dimen name="ndp_477">-522.79dp</dimen>
<dimen name="ndp_478">-523.89dp</dimen>
<dimen name="ndp_479">-524.98dp</dimen>
<dimen name="ndp_480">-526.08dp</dimen>
<dimen name="ndp_481">-527.18dp</dimen>
<dimen name="ndp_482">-528.27dp</dimen>
<dimen name="ndp_483">-529.37dp</dimen>
<dimen name="ndp_484">-530.46dp</dimen>
<dimen name="ndp_485">-531.56dp</dimen>
<dimen name="ndp_486">-532.66dp</dimen>
<dimen name="ndp_487">-533.75dp</dimen>
<dimen name="ndp_488">-534.85dp</dimen>
<dimen name="ndp_489">-535.94dp</dimen>
<dimen name="ndp_490">-537.04dp</dimen>
<dimen name="ndp_491">-538.14dp</dimen>
<dimen name="ndp_492">-539.23dp</dimen>
<dimen name="ndp_493">-540.33dp</dimen>
<dimen name="ndp_494">-541.42dp</dimen>
<dimen name="ndp_495">-542.52dp</dimen>
<dimen name="ndp_496">-543.62dp</dimen>
<dimen name="ndp_497">-544.71dp</dimen>
<dimen name="ndp_498">-545.81dp</dimen>
<dimen name="ndp_499">-546.90dp</dimen>
<dimen name="ndp_500">-548.00dp</dimen>
<dimen name="ndp_501">-549.10dp</dimen>
<dimen name="ndp_502">-550.19dp</dimen>
<dimen name="ndp_503">-551.29dp</dimen>
<dimen name="ndp_504">-552.38dp</dimen>
<dimen name="ndp_505">-553.48dp</dimen>
<dimen name="ndp_506">-554.58dp</dimen>
<dimen name="ndp_507">-555.67dp</dimen>
<dimen name="ndp_508">-556.77dp</dimen>
<dimen name="ndp_509">-557.86dp</dimen>
<dimen name="ndp_510">-558.96dp</dimen>
<dimen name="ndp_511">-560.06dp</dimen>
<dimen name="ndp_512">-561.15dp</dimen>
<dimen name="ndp_513">-562.25dp</dimen>
<dimen name="ndp_514">-563.34dp</dimen>
<dimen name="ndp_515">-564.44dp</dimen>
<dimen name="ndp_516">-565.54dp</dimen>
<dimen name="ndp_517">-566.63dp</dimen>
<dimen name="ndp_518">-567.73dp</dimen>
<dimen name="ndp_519">-568.82dp</dimen>
<dimen name="ndp_520">-569.92dp</dimen>
<dimen name="ndp_521">-571.02dp</dimen>
<dimen name="ndp_522">-572.11dp</dimen>
<dimen name="ndp_523">-573.21dp</dimen>
<dimen name="ndp_524">-574.30dp</dimen>
<dimen name="ndp_525">-575.40dp</dimen>
<dimen name="ndp_526">-576.50dp</dimen>
<dimen name="ndp_527">-577.59dp</dimen>
<dimen name="ndp_528">-578.69dp</dimen>
<dimen name="ndp_529">-579.78dp</dimen>
<dimen name="ndp_530">-580.88dp</dimen>
<dimen name="ndp_531">-581.98dp</dimen>
<dimen name="ndp_532">-583.07dp</dimen>
<dimen name="ndp_533">-584.17dp</dimen>
<dimen name="ndp_534">-585.26dp</dimen>
<dimen name="ndp_535">-586.36dp</dimen>
<dimen name="ndp_536">-587.46dp</dimen>
<dimen name="ndp_537">-588.55dp</dimen>
<dimen name="ndp_538">-589.65dp</dimen>
<dimen name="ndp_539">-590.74dp</dimen>
<dimen name="ndp_540">-591.84dp</dimen>
<dimen name="ndp_541">-592.94dp</dimen>
<dimen name="ndp_542">-594.03dp</dimen>
<dimen name="ndp_543">-595.13dp</dimen>
<dimen name="ndp_544">-596.22dp</dimen>
<dimen name="ndp_545">-597.32dp</dimen>
<dimen name="ndp_546">-598.42dp</dimen>
<dimen name="ndp_547">-599.51dp</dimen>
<dimen name="ndp_548">-600.61dp</dimen>
<dimen name="ndp_549">-601.70dp</dimen>
<dimen name="ndp_550">-602.80dp</dimen>
<dimen name="ndp_551">-603.90dp</dimen>
<dimen name="ndp_552">-604.99dp</dimen>
<dimen name="ndp_553">-606.09dp</dimen>
<dimen name="ndp_554">-607.18dp</dimen>
<dimen name="ndp_555">-608.28dp</dimen>
<dimen name="ndp_556">-609.38dp</dimen>
<dimen name="ndp_557">-610.47dp</dimen>
<dimen name="ndp_558">-611.57dp</dimen>
<dimen name="ndp_559">-612.66dp</dimen>
<dimen name="ndp_560">-613.76dp</dimen>
<dimen name="ndp_561">-614.86dp</dimen>
<dimen name="ndp_562">-615.95dp</dimen>
<dimen name="ndp_563">-617.05dp</dimen>
<dimen name="ndp_564">-618.14dp</dimen>
<dimen name="ndp_565">-619.24dp</dimen>
<dimen name="ndp_566">-620.34dp</dimen>
<dimen name="ndp_567">-621.43dp</dimen>
<dimen name="ndp_568">-622.53dp</dimen>
<dimen name="ndp_569">-623.62dp</dimen>
<dimen name="ndp_570">-624.72dp</dimen>
<dimen name="ndp_571">-625.82dp</dimen>
<dimen name="ndp_572">-626.91dp</dimen>
<dimen name="ndp_573">-628.01dp</dimen>
<dimen name="ndp_574">-629.10dp</dimen>
<dimen name="ndp_575">-630.20dp</dimen>
<dimen name="ndp_576">-631.30dp</dimen>
<dimen name="ndp_577">-632.39dp</dimen>
<dimen name="ndp_578">-633.49dp</dimen>
<dimen name="ndp_579">-634.58dp</dimen>
<dimen name="ndp_580">-635.68dp</dimen>
<dimen name="ndp_581">-636.78dp</dimen>
<dimen name="ndp_582">-637.87dp</dimen>
<dimen name="ndp_583">-638.97dp</dimen>
<dimen name="ndp_584">-640.06dp</dimen>
<dimen name="ndp_585">-641.16dp</dimen>
<dimen name="ndp_586">-642.26dp</dimen>
<dimen name="ndp_587">-643.35dp</dimen>
<dimen name="ndp_588">-644.45dp</dimen>
<dimen name="ndp_589">-645.54dp</dimen>
<dimen name="ndp_590">-646.64dp</dimen>
<dimen name="ndp_591">-647.74dp</dimen>
<dimen name="ndp_592">-648.83dp</dimen>
<dimen name="ndp_593">-649.93dp</dimen>
<dimen name="ndp_594">-651.02dp</dimen>
<dimen name="ndp_595">-652.12dp</dimen>
<dimen name="ndp_596">-653.22dp</dimen>
<dimen name="ndp_597">-654.31dp</dimen>
<dimen name="ndp_598">-655.41dp</dimen>
<dimen name="ndp_599">-656.50dp</dimen>
<dimen name="ndp_600">-657.60dp</dimen>
<dimen name="ndp_601">-658.70dp</dimen>
<dimen name="ndp_602">-659.79dp</dimen>
<dimen name="ndp_603">-660.89dp</dimen>
<dimen name="ndp_604">-661.98dp</dimen>
<dimen name="ndp_605">-663.08dp</dimen>
<dimen name="ndp_606">-664.18dp</dimen>
<dimen name="ndp_607">-665.27dp</dimen>
<dimen name="ndp_608">-666.37dp</dimen>
<dimen name="ndp_609">-667.46dp</dimen>
<dimen name="ndp_610">-668.56dp</dimen>
<dimen name="ndp_611">-669.66dp</dimen>
<dimen name="ndp_612">-670.75dp</dimen>
<dimen name="ndp_613">-671.85dp</dimen>
<dimen name="ndp_614">-672.94dp</dimen>
<dimen name="ndp_615">-674.04dp</dimen>
<dimen name="ndp_616">-675.14dp</dimen>
<dimen name="ndp_617">-676.23dp</dimen>
<dimen name="ndp_618">-677.33dp</dimen>
<dimen name="ndp_619">-678.42dp</dimen>
<dimen name="ndp_620">-679.52dp</dimen>
<dimen name="ndp_621">-680.62dp</dimen>
<dimen name="ndp_622">-681.71dp</dimen>
<dimen name="ndp_623">-682.81dp</dimen>
<dimen name="ndp_624">-683.90dp</dimen>
<dimen name="ndp_625">-685.00dp</dimen>
<dimen name="ndp_626">-686.10dp</dimen>
<dimen name="ndp_627">-687.19dp</dimen>
<dimen name="ndp_628">-688.29dp</dimen>
<dimen name="ndp_629">-689.38dp</dimen>
<dimen name="ndp_630">-690.48dp</dimen>
<dimen name="ndp_631">-691.58dp</dimen>
<dimen name="ndp_632">-692.67dp</dimen>
<dimen name="ndp_633">-693.77dp</dimen>
<dimen name="ndp_634">-694.86dp</dimen>
<dimen name="ndp_635">-695.96dp</dimen>
<dimen name="ndp_636">-697.06dp</dimen>
<dimen name="ndp_637">-698.15dp</dimen>
<dimen name="ndp_638">-699.25dp</dimen>
<dimen name="ndp_639">-700.34dp</dimen>
<dimen name="ndp_640">-701.44dp</dimen>
<dimen name="ndp_641">-702.54dp</dimen>
<dimen name="ndp_642">-703.63dp</dimen>
<dimen name="ndp_643">-704.73dp</dimen>
<dimen name="ndp_644">-705.82dp</dimen>
<dimen name="ndp_645">-706.92dp</dimen>
<dimen name="ndp_646">-708.02dp</dimen>
<dimen name="ndp_647">-709.11dp</dimen>
<dimen name="ndp_648">-710.21dp</dimen>
<dimen name="ndp_649">-711.30dp</dimen>
<dimen name="ndp_650">-712.40dp</dimen>
<dimen name="ndp_651">-713.50dp</dimen>
<dimen name="ndp_652">-714.59dp</dimen>
<dimen name="ndp_653">-715.69dp</dimen>
<dimen name="ndp_654">-716.78dp</dimen>
<dimen name="ndp_655">-717.88dp</dimen>
<dimen name="ndp_656">-718.98dp</dimen>
<dimen name="ndp_657">-720.07dp</dimen>
<dimen name="ndp_658">-721.17dp</dimen>
<dimen name="ndp_659">-722.26dp</dimen>
<dimen name="ndp_660">-723.36dp</dimen>
<dimen name="ndp_661">-724.46dp</dimen>
<dimen name="ndp_662">-725.55dp</dimen>
<dimen name="ndp_663">-726.65dp</dimen>
<dimen name="ndp_664">-727.74dp</dimen>
<dimen name="ndp_665">-728.84dp</dimen>
<dimen name="ndp_666">-729.94dp</dimen>
<dimen name="ndp_667">-731.03dp</dimen>
<dimen name="ndp_668">-732.13dp</dimen>
<dimen name="ndp_669">-733.22dp</dimen>
<dimen name="ndp_670">-734.32dp</dimen>
<dimen name="ndp_671">-735.42dp</dimen>
<dimen name="ndp_672">-736.51dp</dimen>
<dimen name="ndp_673">-737.61dp</dimen>
<dimen name="ndp_674">-738.70dp</dimen>
<dimen name="ndp_675">-739.80dp</dimen>
<dimen name="ndp_676">-740.90dp</dimen>
<dimen name="ndp_677">-741.99dp</dimen>
<dimen name="ndp_678">-743.09dp</dimen>
<dimen name="ndp_679">-744.18dp</dimen>
<dimen name="ndp_680">-745.28dp</dimen>
<dimen name="ndp_681">-746.38dp</dimen>
<dimen name="ndp_682">-747.47dp</dimen>
<dimen name="ndp_683">-748.57dp</dimen>
<dimen name="ndp_684">-749.66dp</dimen>
<dimen name="ndp_685">-750.76dp</dimen>
<dimen name="ndp_686">-751.86dp</dimen>
<dimen name="ndp_687">-752.95dp</dimen>
<dimen name="ndp_688">-754.05dp</dimen>
<dimen name="ndp_689">-755.14dp</dimen>
<dimen name="ndp_690">-756.24dp</dimen>
<dimen name="ndp_691">-757.34dp</dimen>
<dimen name="ndp_692">-758.43dp</dimen>
<dimen name="ndp_693">-759.53dp</dimen>
<dimen name="ndp_694">-760.62dp</dimen>
<dimen name="ndp_695">-761.72dp</dimen>
<dimen name="ndp_696">-762.82dp</dimen>
<dimen name="ndp_697">-763.91dp</dimen>
<dimen name="ndp_698">-765.01dp</dimen>
<dimen name="ndp_699">-766.10dp</dimen>
<dimen name="ndp_700">-767.20dp</dimen>
<dimen name="ndp_701">-768.30dp</dimen>
<dimen name="ndp_702">-769.39dp</dimen>
<dimen name="ndp_703">-770.49dp</dimen>
<dimen name="ndp_704">-771.58dp</dimen>
<dimen name="ndp_705">-772.68dp</dimen>
<dimen name="ndp_706">-773.78dp</dimen>
<dimen name="ndp_707">-774.87dp</dimen>
<dimen name="ndp_708">-775.97dp</dimen>
<dimen name="ndp_709">-777.06dp</dimen>
<dimen name="ndp_710">-778.16dp</dimen>
<dimen name="ndp_711">-779.26dp</dimen>
<dimen name="ndp_712">-780.35dp</dimen>
<dimen name="ndp_713">-781.45dp</dimen>
<dimen name="ndp_714">-782.54dp</dimen>
<dimen name="ndp_715">-783.64dp</dimen>
<dimen name="ndp_716">-784.74dp</dimen>
<dimen name="ndp_717">-785.83dp</dimen>
<dimen name="ndp_718">-786.93dp</dimen>
<dimen name="ndp_719">-788.02dp</dimen>
<dimen name="ndp_720">-789.12dp</dimen>
<dimen name="ndp_721">-790.22dp</dimen>
<dimen name="ndp_722">-791.31dp</dimen>
<dimen name="ndp_723">-792.41dp</dimen>
<dimen name="ndp_724">-793.50dp</dimen>
<dimen name="ndp_725">-794.60dp</dimen>
<dimen name="ndp_726">-795.70dp</dimen>
<dimen name="ndp_727">-796.79dp</dimen>
<dimen name="ndp_728">-797.89dp</dimen>
<dimen name="ndp_729">-798.98dp</dimen>
<dimen name="ndp_730">-800.08dp</dimen>
<dimen name="ndp_731">-801.18dp</dimen>
<dimen name="ndp_732">-802.27dp</dimen>
<dimen name="ndp_733">-803.37dp</dimen>
<dimen name="ndp_734">-804.46dp</dimen>
<dimen name="ndp_735">-805.56dp</dimen>
<dimen name="ndp_736">-806.66dp</dimen>
<dimen name="ndp_737">-807.75dp</dimen>
<dimen name="ndp_738">-808.85dp</dimen>
<dimen name="ndp_739">-809.94dp</dimen>
<dimen name="ndp_740">-811.04dp</dimen>
<dimen name="ndp_741">-812.14dp</dimen>
<dimen name="ndp_742">-813.23dp</dimen>
<dimen name="ndp_743">-814.33dp</dimen>
<dimen name="ndp_744">-815.42dp</dimen>
<dimen name="ndp_745">-816.52dp</dimen>
<dimen name="ndp_746">-817.62dp</dimen>
<dimen name="ndp_747">-818.71dp</dimen>
<dimen name="ndp_748">-819.81dp</dimen>
<dimen name="ndp_749">-820.90dp</dimen>
<dimen name="ndp_750">-822.00dp</dimen>
</resources>
